pynoob/Net.py
pynoob/Newton.py
pynoob/__init__.py
pynoob/augmentation.py
pynoob/data.py
pynoob/data_summary.py
pynoob/gradCAM.py
pynoob/grad_model.py
pynoob/graphs.py
pynoob/plot.py
pynoob/runner.py
pynoob/summary.py
pynoob/test.py
pynoob/train.py
pynoob/load_data/__init__.py
pynoob/load_data/augmentation.py
pynoob/load_data/data.py
pynoob/load_data/data_summary.py
pynoob/models/CusResNet.py
pynoob/models/Net.py
pynoob/models/S11_model.py
pynoob/models/__init__.py
pynoob/plotting/__init__.py
pynoob/plotting/gradCAM.py
pynoob/plotting/graphs.py
pynoob/plotting/plot.py
pynoob/training/__init__.py
pynoob/training/find_lr.py
pynoob/training/range_test.py
pynoob/training/test.py
pynoob/training/train.py
pynoob-0.1.0.51.dist-info/LICENSE
pynoob-0.1.0.51.dist-info/METADATA
pynoob-0.1.0.51.dist-info/WHEEL
pynoob-0.1.0.51.dist-info/top_level.txt
pynoob-0.1.0.51.dist-info/RECORD
