Metadata-Version: 2.1
Name: pynoob
Version: 0.1.0.51
Summary: A n00b DeepLearning Package
Home-page: https://github.com/abksyed/pynoob
Author: Syed Abdul K
Author-email: abdksyed@gmail.com
License: UNKNOWN
Download-URL: https://github.com/abksyed/pynoob/dist/pynoob-0.1.0.51.tar.gz
Platform: UNKNOWN
Classifier: Programming Language :: Python :: 3
Classifier: License :: OSI Approved :: MIT License
Classifier: Operating System :: OS Independent
Requires-Python: >=3.6
Requires-Dist: albumentations (==0.4.5)
Requires-Dist: tqdm
Requires-Dist: numpy
Requires-Dist: matplotlib
Requires-Dist: torch
Requires-Dist: torchvision
Requires-Dist: torchsummary
